{
  "newNotePlaceholder": "Untitled",
  "defaultInitialization": false,
  "filePreviewOnHover": false,
  "flowMenuEnabled": true,
  "markSans": false,
  "blinkEnabled": true,
  "makeMenuPlaceholder": true,
  "mobileMakeBar": true,
  "inlineStyler": true,
  "makerMode": true,
  "spacesMDBInHidden": true,
  "inlineStylerColors": false,
  "editorFlow": true,
  "internalLinkClickFlow": true,
  "contextEnabled": false,
  "spaceViewEnabled": false,
  "saveAllContextToFrontmatter": true,
  "editorFlowStyle": "seamless",
  "autoOpenFileContext": false,
  "activeView": "/",
  "hideFrontmatter": true,
  "activeSpace": "",
  "defaultDateFormat": "MMM dd yyyy",
  "spacesEnabled": false,
  "spacesPerformance": false,
  "enableFolderNote": true,
  "folderIndentationLines": true,
  "revealActiveFile": false,
  "spacesStickers": true,
  "spaceRowHeight": 29,
  "spacesDisablePatch": false,
  "folderNoteInsideFolder": true,
  "sidebarTabs": true,
  "showRibbon": true,
  "deleteFileOption": "trash",
  "expandedSpaces": [
    "/",
    "//Spaces",
    "//Spaces",
    "//무제 폴더",
    "//스프링 검증 추가하기무제 폴더",
    "//스프링 검증 추가하기무스프링 검증 추가하기무제 폴더",
    "//스프링 검증 추가하기",
    "//스프링 검증 추가하기",
    "//스프링 검증 추가하기",
    "//스프링 검증 추가하기",
    "//프로젝트",
    "//Spaces",
    "//프로젝트",
    "//프로젝트",
    "//Area",
    "//Spaces/Spaces/Home",
    "//Spaces",
    "//Spaces/Spaces/Home",
    "//Spaces",
    "//Spaces/Spaces/Home",
    "//Spaces/Spaces/Home",
    "//Spaces/Spaces/Home",
    "//Spaces/Spaces/Home",
    "//Spaces/Spaces/Home",
    "//Archive",
    "//Area",
    "//Archive",
    "//Fonts",
    "//Spaces",
    "//프로젝트",
    "//Area",
    "//Resource",
    "//Resource",
    "//Resource",
    "//4. 스프링 RestAPI만들기",
    "//3. 스프링과 jsp로 Todo앱만들기",
    "//Resource/Resource/4. 스프링 RestAPI만들기/Resource/4. 스프링 RestAPI만들기/오류 정리",
    "//Resource/Resource/4. 스프링 RestAPI만들기/Resource/4. 스프링 RestAPI만들기/오류 정리",
    "//Resource/Resource/4. 스프링 RestAPI만들기/Resource/4. 스프링 RestAPI만들기/오류 정리",
    "//Resource/Resource/4. 스프링 RestAPI만들기/Resource/4. 스프링 RestAPI만들기/새로 안 정보",
    "//템플릿",
    "//Resource/Resource/4. 스프링 RestAPI만들기/Resource/4. 스프링 RestAPI만들기/새로 안 정보",
    "//Resource/Resource/4. 스프링 RestAPI만들기/Resource/4. 스프링 RestAPI만들기/새로 안 정보",
    "//Resource/Resource/4. 스프링 RestAPI만들기/Resource/4. 스프링 RestAPI만들기/새로 안 정보",
    "//Resource/Resource/4. 스프링 RestAPI만들기/Resource/4. 스프링 RestAPI만들기/새로 안 정보",
    "//Resource/Resource/4. 스프링 RestAPI만들기/Resource/4. 스프링 RestAPI만들기/새로 안 정보",
    "//Resource",
    "//프로젝트",
    "//Resource",
    "//Resource",
    "//프로젝트",
    "//Resource",
    "//프로젝트",
    "//Spaces/Spaces/Home",
    "//Spaces",
    "//Spaces/Spaces/Home/Spaces/Home/프로그래밍과 논리",
    "//Spaces/Spaces/Home/Spaces/Home/프로그래밍과 논리",
    "//Spaces/Spaces/Home/Spaces/Home/프로그래밍과 논리",
    "//Spaces/Spaces/Home/Spaces/Home/프로그래밍과 논리",
    "//Spaces/Spaces/Home/Spaces/Home/프로그래밍과 논리/Spaces/Home/프로그래밍과 논리/수학적 귀납법 문제들",
    "//Spaces/Spaces/Home/Spaces/Home/프로그래밍과 논리/Spaces/Home/프로그래밍과 논리/수학적 귀납법 문제들",
    "//Spaces/Spaces/Home/Spaces/Home/프로그래밍과 논리/Spaces/Home/프로그래밍과 논리/수학적 귀납법 문제들",
    "//Spaces/Spaces/Home/Spaces/Home/프로그래밍과 논리/Spaces/Home/프로그래밍과 논리/수학적 귀납법 문제들",
    "//Spaces/Spaces/Home/Spaces/Home/프로그래밍과 논리/Spaces/Home/프로그래밍과 논리/수학적 귀납법 문제들",
    "//Spaces/Spaces/Home/Spaces/Home/프로그래밍과 논리/Spaces/Home/프로그래밍과 논리/수학적 귀납법 문제들",
    "//Spaces/Spaces/Home/Spaces/Home/프로그래밍과 논리/Spaces/Home/프로그래밍과 논리/수학적 귀납법 문제들",
    "//Spaces/Spaces/Home/Spaces/Home/프로그래밍과 논리",
    "//Spaces/Spaces/Home/Spaces/Home/프로그래밍과 논리",
    "//Spaces/Spaces/Home/Spaces/Home/프로그래밍과 논리/Spaces/Home/프로그래밍과 논리/프로그래밍과 논리 문제들"
  ],
  "expandFolderOnClick": true,
  "menuTriggerChar": "/",
  "inlineStickerMenu": true,
  "emojiTriggerChar": ":",
  "folderContextFile": "context",
  "folderFrameFile": "frames",
  "spacesFolder": "Spaces",
  "hiddenFiles": [
    "Excalidraw"
  ],
  "hiddenExtensions": [
    ".mdb"
  ],
  "inlineBacklinks": false,
  "inlineContext": true,
  "inlineBacklinksExpanded": false,
  "inlineContextExpanded": false,
  "inlineContextSectionsExpanded": true,
  "dataviewInlineContext": false,
  "inlineContextNameLayout": "vertical",
  "waypoints": [
    "Spaces/Home",
    "/",
    "spaces://$tags"
  ],
  "spacesUseAlias": false,
  "fmKeyAlias": "aliases",
  "fmKeyBanner": "banner",
  "fmKeyColor": "color",
  "fmKeySticker": "sticker",
  "fmKeyContexts": "_contexts",
  "fmKeySort": "_sort",
  "fmKeyFilter": "_filters",
  "fmKeyLinks": "_links",
  "openSpacesOnLaunch": true,
  "indexSVG": false,
  "quickFrames": [],
  "readableLineWidth": true,
  "autoAddContextsToSubtags": true,
  "autoMigration08": false,
  "releaseNotesPrompt": 0.815,
  "enableDefaultSpaces": false,
  "enableTagSpaces": false,
  "enableHomeSpace": false,
  "showSpacePinIcon": true,
  "minimalFix": false,
  "experimental": false,
  "systemName": "Vault"
}